pytorch_common/__init__.py
pytorch_common/callbacks/__init__.py
pytorch_common/callbacks/callback.py
pytorch_common/callbacks/callback_manager.py
pytorch_common/callbacks/early_stop.py
pytorch_common/callbacks/mixin/metric_improve_mixin.py
pytorch_common/callbacks/output/__init__.py
pytorch_common/callbacks/output/logger_callback.py
pytorch_common/callbacks/output/output_callback.py
pytorch_common/callbacks/output/output_hook_callback.py
pytorch_common/callbacks/output/plot/__init__.py
pytorch_common/callbacks/output/plot/metric_logger.py
pytorch_common/callbacks/output/plot/metrics_plotter.py
pytorch_common/callbacks/reduce_lr_on_plateau.py
pytorch_common/callbacks/save_best_model_checkpoint.py
pytorch_common/callbacks/validation.py
pytorch_common/error/__init__.py
pytorch_common/error/assertions.py
pytorch_common/error/checker.py
pytorch_common/error/common_exception.py
pytorch_common/kfoldcv/__init__.py
pytorch_common/kfoldcv/k_fold_cv.py
pytorch_common/kfoldcv/strategy/__init__.py
pytorch_common/kfoldcv/strategy/k_fold_cv_strategy.py
pytorch_common/kfoldcv/strategy/non_parallel_k_fold_cv_strategy.py
pytorch_common/kfoldcv/strategy/parallel_k_fold_cv_strategy.py
pytorch_common/modules/__init__.py
pytorch_common/modules/common_mixin.py
pytorch_common/modules/fit_context.py
pytorch_common/modules/fit_mixin.py
pytorch_common/modules/fn.py
pytorch_common/modules/persistent_mixin.py
pytorch_common/modules/predict_mixin.py
pytorch_common/plot/__init__.py
pytorch_common/plot/plot_loss.py
pytorch_common/util/__init__.py
pytorch_common/util/data_utils.py
pytorch_common/util/device_utils.py
pytorch_common/util/dict_utils.py
pytorch_common/util/logger.py
pytorch_common/util/module_utils.py
pytorch_common/util/os_utils.py
pytorch_common/util/stopwatch.py
pytorch_common/util/tensor_utils.py
pytorch_common/util/weights_file_resolver.py
pytorch_common-0.3.8.dist-info/METADATA
pytorch_common-0.3.8.dist-info/WHEEL
pytorch_common-0.3.8.dist-info/RECORD
