Metadata-Version: 2.1
Name: pytorch-common
Version: 0.3.8
Summary: Common torch tools and extension
Home-page: https://github.com/adrianmarino/pytorch-common/tree/master
License: MIT
Keywords: pytorch,common
Author: adrianmarino
Author-email: adrianmarino@gmail.com
Requires-Python: >=3.7
Classifier: License :: OSI Approved :: MIT License
Classifier: Programming Language :: Python :: 3
Classifier: Programming Language :: Python :: 3.7
Classifier: Programming Language :: Python :: 3.8
Classifier: Programming Language :: Python :: 3.9
Classifier: Programming Language :: Python :: 3.10
Classifier: Programming Language :: Python :: 3.11
Requires-Dist: bunch (>=1.0.1)
Requires-Dist: ipython (>=7.31.0)
Requires-Dist: matplotlib (>=3.5.1)
Requires-Dist: numpy (>=1.20)
Requires-Dist: scikit-learn (>=1.0.2)
Requires-Dist: seaborn (>=0.11.2)
Requires-Dist: torch (>=1.10.1)
Project-URL: Repository, https://github.com/adrianmarino/pytorch-common/tree/master
